{
  "unpublishedPage": {
    "name": "Cadastrar Usuario",
    "slug": "cadastrar-usuario",
    "layouts": [
      {
        "viewMode": false,
        "dsl": {
          "widgetName": "MainContainer",
          "backgroundColor": "none",
          "rightColumn": 4896,
          "snapColumns": 64,
          "detachFromLayout": true,
          "widgetId": "0",
          "topRow": 0,
          "bottomRow": 580,
          "containerStyle": "none",
          "snapRows": 124,
          "parentRowSpace": 1,
          "type": "CANVAS_WIDGET",
          "canExtend": true,
          "version": 87,
          "minHeight": 1292,
          "dynamicTriggerPathList": [],
          "parentColumnSpace": 1,
          "dynamicBindingPathList": [],
          "leftColumn": 0
        },
        "layoutOnLoadActions": [],
        "layoutOnLoadActionErrors": [],
        "validOnPageLoadActions": true,
        "id": "Cadastrar Usuario",
        "deleted": false,
        "policies": [],
        "userPermissions": []
      }
    ],
    "userPermissions": [],
    "policies": [],
    "isHidden": false
  },
  "deleted": false,
  "gitSyncId": "65f9b5f30f108844aba2b343_65f9b6da0f108844aba2b3cf"
}